{
"meta":{"test_sets":[],"test_metrics":[],"learn_metrics":[{"best_value":"Min","name":"MAE"}],"launch_mode":"Train","parameters":"","iteration_count":500,"learn_sets":["learn"],"name":"experiment"},
"iterations":[
{"learn":[133596.2084],"iteration":0,"passed_time":0.3134654164,"remaining_time":156.4192428},
{"learn":[133353.4393],"iteration":1,"passed_time":0.6194782107,"remaining_time":154.2500745},
{"learn":[133165.3994],"iteration":2,"passed_time":0.9291903668,"remaining_time":153.9358708},
{"learn":[132937.8424],"iteration":3,"passed_time":1.255024878,"remaining_time":155.6230849},
{"learn":[132695.2512],"iteration":4,"passed_time":1.580825133,"remaining_time":156.5016881},
{"learn":[132439.0225],"iteration":5,"passed_time":1.888936898,"remaining_time":155.5224713},
{"learn":[132063.4361],"iteration":6,"passed_time":2.204713774,"remaining_time":155.2748415},
{"learn":[131872.1024],"iteration":7,"passed_time":2.519723369,"remaining_time":154.9629872},
{"learn":[131661.4218],"iteration":8,"passed_time":2.824711769,"remaining_time":154.1037199},
{"learn":[131395.1675],"iteration":9,"passed_time":3.136342269,"remaining_time":153.6807712},
{"learn":[131218.814],"iteration":10,"passed_time":3.447125366,"remaining_time":153.2403913},
{"learn":[131088.4818],"iteration":11,"passed_time":3.49716422,"remaining_time":142.2180116},
{"learn":[130926.8227],"iteration":12,"passed_time":3.803662642,"remaining_time":142.4910544},
{"learn":[130759.5004],"iteration":13,"passed_time":4.112200097,"remaining_time":142.7520891},
{"learn":[130630.8974],"iteration":14,"passed_time":4.418326649,"remaining_time":142.8592283},
{"learn":[130427.0831],"iteration":15,"passed_time":4.719361219,"remaining_time":142.7606769},
{"learn":[130268.3707],"iteration":16,"passed_time":5.031967833,"remaining_time":142.9670861},
{"learn":[130102.0933],"iteration":17,"passed_time":5.349042093,"remaining_time":143.2354605},
{"learn":[129937.379],"iteration":18,"passed_time":5.665920921,"remaining_time":143.4372612},
{"learn":[129570.9223],"iteration":19,"passed_time":5.982711714,"remaining_time":143.5850811},
{"learn":[129359.7777],"iteration":20,"passed_time":6.294172905,"remaining_time":143.5670867},
{"learn":[129220.5118],"iteration":21,"passed_time":6.601898866,"remaining_time":143.4412572},
{"learn":[129053.1933],"iteration":22,"passed_time":6.912533809,"remaining_time":143.3599403},
{"learn":[128923.2656],"iteration":23,"passed_time":7.230219704,"remaining_time":143.3993575},
{"learn":[128776.0582],"iteration":24,"passed_time":7.540385846,"remaining_time":143.2673311},
{"learn":[128652.9992],"iteration":25,"passed_time":7.693279473,"remaining_time":140.2544027},
{"learn":[128486.0675],"iteration":26,"passed_time":8.003376782,"remaining_time":140.2073044},
{"learn":[128391.2172],"iteration":27,"passed_time":8.313562587,"remaining_time":140.1429122},
{"learn":[128305.0482],"iteration":28,"passed_time":8.346971982,"remaining_time":135.5663381},
{"learn":[128210.0859],"iteration":29,"passed_time":8.431558602,"remaining_time":132.0944181},
{"learn":[128021.6006],"iteration":30,"passed_time":8.743999174,"remaining_time":132.2882456},
{"learn":[127867.3718],"iteration":31,"passed_time":9.052370396,"remaining_time":132.390917},
{"learn":[127699.8157],"iteration":32,"passed_time":9.358456941,"remaining_time":132.4363452},
{"learn":[127524.9398],"iteration":33,"passed_time":9.670021613,"remaining_time":132.5361786},
{"learn":[127379.9327],"iteration":34,"passed_time":9.973299501,"remaining_time":132.5024077},
{"learn":[127275.1459],"iteration":35,"passed_time":10.27848417,"remaining_time":132.4782405},
{"learn":[127165.3919],"iteration":36,"passed_time":10.59130702,"remaining_time":132.5344636},
{"learn":[127063.1801],"iteration":37,"passed_time":10.89963112,"remaining_time":132.5165678},
{"learn":[126963.0903],"iteration":38,"passed_time":11.21072159,"remaining_time":132.5164783},
{"learn":[126860.7065],"iteration":39,"passed_time":11.5213843,"remaining_time":132.4959194},
{"learn":[126762.6943],"iteration":40,"passed_time":11.83096705,"remaining_time":132.4491189},
{"learn":[126613.3476],"iteration":41,"passed_time":12.14106461,"remaining_time":132.3954189},
{"learn":[126484.1034],"iteration":42,"passed_time":12.45332713,"remaining_time":132.3528023},
{"learn":[126390.3187],"iteration":43,"passed_time":12.7605835,"remaining_time":132.2460472},
{"learn":[126294.8638],"iteration":44,"passed_time":13.07068809,"remaining_time":132.1591796},
{"learn":[126155.0289],"iteration":45,"passed_time":13.37846413,"remaining_time":132.0396243},
{"learn":[125927.9231],"iteration":46,"passed_time":13.68791295,"remaining_time":131.9281822},
{"learn":[125792.3323],"iteration":47,"passed_time":13.99850925,"remaining_time":131.8192954},
{"learn":[125498.589],"iteration":48,"passed_time":14.30285071,"remaining_time":131.6446055},
{"learn":[125379.4771],"iteration":49,"passed_time":14.61517825,"remaining_time":131.5366042},
{"learn":[125226.5212],"iteration":50,"passed_time":14.92174588,"remaining_time":131.3698804},
{"learn":[125202.1816],"iteration":51,"passed_time":14.93594037,"remaining_time":128.6788709},
{"learn":[125023.1218],"iteration":52,"passed_time":15.24908209,"remaining_time":128.610183},
{"learn":[124948.3489],"iteration":53,"passed_time":15.55106115,"remaining_time":128.4402458},
{"learn":[124849.3545],"iteration":54,"passed_time":15.85352394,"remaining_time":128.2694209},
{"learn":[124509.5819],"iteration":55,"passed_time":16.16691022,"remaining_time":128.1805025},
{"learn":[124459.1336],"iteration":56,"passed_time":16.46555888,"remaining_time":127.9691681},
{"learn":[124371.4472],"iteration":57,"passed_time":16.77206883,"remaining_time":127.8147314},
{"learn":[124287.3263],"iteration":58,"passed_time":17.08135694,"remaining_time":127.6759053},
{"learn":[124162.3467],"iteration":59,"passed_time":17.3874274,"remaining_time":127.5078009},
{"learn":[123982.1837],"iteration":60,"passed_time":17.69563997,"remaining_time":127.3505893},
{"learn":[123912.9501],"iteration":61,"passed_time":18.00416856,"remaining_time":127.1907392},
{"learn":[123525.8049],"iteration":62,"passed_time":18.31913521,"remaining_time":127.0708268},
{"learn":[123435.092],"iteration":63,"passed_time":18.63006557,"remaining_time":126.9173217},
{"learn":[123367.2565],"iteration":64,"passed_time":18.9406383,"remaining_time":126.7565794},
{"learn":[123242.598],"iteration":65,"passed_time":19.25131485,"remaining_time":126.5919794},
{"learn":[123182.5861],"iteration":66,"passed_time":19.55160707,"remaining_time":126.3559084},
{"learn":[122992.7055],"iteration":67,"passed_time":19.85964356,"remaining_time":126.1671473},
{"learn":[122925.0763],"iteration":68,"passed_time":20.16914155,"remaining_time":125.9840581},
{"learn":[122856.163],"iteration":69,"passed_time":20.4807624,"remaining_time":125.8103976},
{"learn":[122663.3401],"iteration":70,"passed_time":20.78295142,"remaining_time":125.5758614},
{"learn":[122501.1269],"iteration":71,"passed_time":21.08130545,"remaining_time":125.316649},
{"learn":[122400.4236],"iteration":72,"passed_time":21.38658837,"remaining_time":125.0968936},
{"learn":[122322.4167],"iteration":73,"passed_time":21.70116522,"remaining_time":124.9283295},
{"learn":[122244.4377],"iteration":74,"passed_time":22.00670756,"remaining_time":124.7046761},
{"learn":[122159.6164],"iteration":75,"passed_time":22.32008369,"remaining_time":124.5225722},
{"learn":[121847.8662],"iteration":76,"passed_time":22.63627354,"remaining_time":124.3525157},
{"learn":[121609.911],"iteration":77,"passed_time":22.94942881,"remaining_time":124.1622943},
{"learn":[121464.9714],"iteration":78,"passed_time":23.25703624,"remaining_time":123.9393957},
{"learn":[121139.1138],"iteration":79,"passed_time":23.56489249,"remaining_time":123.7156856},
{"learn":[121065.8863],"iteration":80,"passed_time":23.86611563,"remaining_time":123.4555858},
{"learn":[120981.938],"iteration":81,"passed_time":24.17290826,"remaining_time":123.2228738},
{"learn":[120800.5105],"iteration":82,"passed_time":24.48034574,"remaining_time":122.9916166},
{"learn":[120724.5392],"iteration":83,"passed_time":24.79059798,"remaining_time":122.7724853},
{"learn":[120603.2966],"iteration":84,"passed_time":25.0962914,"remaining_time":122.5289521},
{"learn":[120547.2695],"iteration":85,"passed_time":25.412489,"remaining_time":122.3345401},
{"learn":[120247.649],"iteration":86,"passed_time":25.7231484,"remaining_time":122.1110378},
{"learn":[120197.6927],"iteration":87,"passed_time":26.02959636,"remaining_time":121.8658375},
{"learn":[120076.0673],"iteration":88,"passed_time":26.34379345,"remaining_time":121.6550462},
{"learn":[119963.4168],"iteration":89,"passed_time":26.65670023,"remaining_time":121.4360788},
{"learn":[119831.0592],"iteration":90,"passed_time":26.97019987,"remaining_time":121.2177115},
{"learn":[119592.3269],"iteration":91,"passed_time":27.2870234,"remaining_time":121.0120168},
{"learn":[119261.9146],"iteration":92,"passed_time":27.59669198,"remaining_time":120.7726197},
{"learn":[119096.1632],"iteration":93,"passed_time":27.90686512,"remaining_time":120.5339068},
{"learn":[118957.5504],"iteration":94,"passed_time":28.21009168,"remaining_time":120.2640751},
{"learn":[118850.5805],"iteration":95,"passed_time":28.52156232,"remaining_time":120.0282414},
{"learn":[118801.3914],"iteration":96,"passed_time":28.8305039,"remaining_time":119.7803409},
{"learn":[118717.8017],"iteration":97,"passed_time":29.14575755,"remaining_time":119.5570871},
{"learn":[118663.2378],"iteration":98,"passed_time":29.45275437,"remaining_time":119.2985303},
{"learn":[118576.7653],"iteration":99,"passed_time":29.7636474,"remaining_time":119.0545896},
{"learn":[118511.4588],"iteration":100,"passed_time":30.07775134,"remaining_time":118.8220078},
{"learn":[118466.4475],"iteration":101,"passed_time":30.38833503,"remaining_time":118.5740916},
{"learn":[118457.9724],"iteration":102,"passed_time":30.40235059,"remaining_time":117.1818756},
{"learn":[118341.3602],"iteration":103,"passed_time":30.71432926,"remaining_time":116.9507153},
{"learn":[118284.484],"iteration":104,"passed_time":31.03311336,"remaining_time":116.7436169},
{"learn":[118138.4225],"iteration":105,"passed_time":31.35194709,"remaining_time":116.5345958},
{"learn":[118108.2954],"iteration":106,"passed_time":31.38329263,"remaining_time":115.2676075},
{"learn":[117971.4399],"iteration":107,"passed_time":31.69825314,"remaining_time":115.0529188},
{"learn":[117879.9624],"iteration":108,"passed_time":32.01300422,"remaining_time":114.835639},
{"learn":[117827.6777],"iteration":109,"passed_time":32.33107774,"remaining_time":114.6283665},
{"learn":[117752.9101],"iteration":110,"passed_time":32.64148061,"remaining_time":114.3922158},
{"learn":[117678.9353],"iteration":111,"passed_time":32.95047518,"remaining_time":114.1498605},
{"learn":[117626.3443],"iteration":112,"passed_time":33.25436385,"remaining_time":113.888839},
{"learn":[117327.0186],"iteration":113,"passed_time":33.56380627,"remaining_time":113.6458703},
{"learn":[117255.0277],"iteration":114,"passed_time":33.87087069,"remaining_time":113.3937845},
{"learn":[117149.5664],"iteration":115,"passed_time":34.17979788,"remaining_time":113.1469171},
{"learn":[117109.6168],"iteration":116,"passed_time":34.486211,"remaining_time":112.8907591},
{"learn":[117083.4463],"iteration":117,"passed_time":34.79042639,"remaining_time":112.6266346},
{"learn":[117046.4139],"iteration":118,"passed_time":34.81448251,"remaining_time":111.4648558},
{"learn":[116888.3691],"iteration":119,"passed_time":35.12485511,"remaining_time":111.2287078},
{"learn":[116835.7998],"iteration":120,"passed_time":35.4331229,"remaining_time":110.9847403},
{"learn":[116720.2158],"iteration":121,"passed_time":35.74644509,"remaining_time":110.7553791},
{"learn":[116686.5742],"iteration":122,"passed_time":36.05212977,"remaining_time":110.5012433},
{"learn":[116600.8629],"iteration":123,"passed_time":36.35696076,"remaining_time":110.2436875},
{"learn":[116564.8591],"iteration":124,"passed_time":36.66301565,"remaining_time":109.989047},
{"learn":[116551.8046],"iteration":125,"passed_time":36.68719894,"remaining_time":108.8969238},
{"learn":[116503.7181],"iteration":126,"passed_time":36.99521743,"remaining_time":108.6552449},
{"learn":[116431.1008],"iteration":127,"passed_time":37.30856734,"remaining_time":108.4280238},
{"learn":[116315.3693],"iteration":128,"passed_time":37.62376828,"remaining_time":108.2047909},
{"learn":[116240.6704],"iteration":129,"passed_time":37.6477785,"remaining_time":107.1513696},
{"learn":[116188.5118],"iteration":130,"passed_time":37.95761216,"remaining_time":106.9187701},
{"learn":[116119.0061],"iteration":131,"passed_time":38.27303437,"remaining_time":106.7005807},
{"learn":[115984.3006],"iteration":132,"passed_time":38.57735438,"remaining_time":106.4502937},
{"learn":[115945.3137],"iteration":133,"passed_time":38.88432793,"remaining_time":106.2064479},
{"learn":[115903.7261],"iteration":134,"passed_time":39.19593354,"remaining_time":105.9741907},
{"learn":[115867.999],"iteration":135,"passed_time":39.21592241,"remaining_time":104.9602629},
{"learn":[115650.762],"iteration":136,"passed_time":39.51741912,"remaining_time":104.7067383},
{"learn":[115583.576],"iteration":137,"passed_time":39.82100088,"remaining_time":104.4579878},
{"learn":[115513.3345],"iteration":138,"passed_time":40.12812752,"remaining_time":104.2176549},
{"learn":[115322.1568],"iteration":139,"passed_time":40.43288229,"remaining_time":103.9702688},
{"learn":[115269.4089],"iteration":140,"passed_time":40.73579762,"remaining_time":103.7173854},
{"learn":[115227.4361],"iteration":141,"passed_time":41.03781928,"remaining_time":103.4615444},
{"learn":[115004.9456],"iteration":142,"passed_time":41.3463607,"remaining_time":103.2213341},
{"learn":[114888.2488],"iteration":143,"passed_time":41.65436585,"remaining_time":102.9788489},
{"learn":[114834.963],"iteration":144,"passed_time":41.96100775,"remaining_time":102.7321224},
{"learn":[114819.553],"iteration":145,"passed_time":41.99265577,"remaining_time":101.8178092},
{"learn":[114782.9594],"iteration":146,"passed_time":42.30727018,"remaining_time":101.5950093},
{"learn":[114754.2864],"iteration":147,"passed_time":42.35862258,"remaining_time":100.7448321},
{"learn":[114612.5839],"iteration":148,"passed_time":42.37386537,"remaining_time":99.82031373},
{"learn":[114493.2633],"iteration":149,"passed_time":42.68543644,"remaining_time":99.59935169},
{"learn":[114419.8328],"iteration":150,"passed_time":42.99739464,"remaining_time":99.37808429},
{"learn":[114395.6371],"iteration":151,"passed_time":43.30110947,"remaining_time":99.13675063},
{"learn":[114391.4587],"iteration":152,"passed_time":43.31663619,"remaining_time":98.24099841},
{"learn":[114354.6655],"iteration":153,"passed_time":43.6164959,"remaining_time":97.99550377},
{"learn":[114227.7334],"iteration":154,"passed_time":43.91997947,"remaining_time":97.75737366},
{"learn":[114212.3748],"iteration":155,"passed_time":43.93625134,"remaining_time":96.88506706},
{"learn":[114152.0574],"iteration":156,"passed_time":44.25115841,"remaining_time":96.67609767},
{"learn":[114115.8239],"iteration":157,"passed_time":44.56281229,"remaining_time":96.45874559},
{"learn":[113937.944],"iteration":158,"passed_time":44.86297756,"remaining_time":96.21556822},
{"learn":[113888.7865],"iteration":159,"passed_time":45.16992883,"remaining_time":95.98609876},
{"learn":[113851.2016],"iteration":160,"passed_time":45.48223716,"remaining_time":95.76694657},
{"learn":[113750.6613],"iteration":161,"passed_time":45.79089891,"remaining_time":95.539036},
{"learn":[113676.0704],"iteration":162,"passed_time":46.09928754,"remaining_time":95.30956994},
{"learn":[113644.2646],"iteration":163,"passed_time":46.40364456,"remaining_time":95.07088154},
{"learn":[113575.9222],"iteration":164,"passed_time":46.71570179,"remaining_time":94.84703091},
{"learn":[113523.5377],"iteration":165,"passed_time":47.02836551,"remaining_time":94.62333784},
{"learn":[113455.1255],"iteration":166,"passed_time":47.34087133,"remaining_time":94.39826439},
{"learn":[113251.8517],"iteration":167,"passed_time":47.64437994,"remaining_time":94.15436988},
{"learn":[113200.0198],"iteration":168,"passed_time":47.95213792,"remaining_time":93.91809262},
{"learn":[113178.6456],"iteration":169,"passed_time":48.25664258,"remaining_time":93.67465912},
{"learn":[113087.9572],"iteration":170,"passed_time":48.56732291,"remaining_time":93.44239321},
{"learn":[113045.6465],"iteration":171,"passed_time":48.88022191,"remaining_time":93.21344643},
{"learn":[112988.4073],"iteration":172,"passed_time":49.1868446,"remaining_time":92.9716658},
{"learn":[112943.8921],"iteration":173,"passed_time":49.23534391,"remaining_time":92.24552939},
{"learn":[112884.0389],"iteration":174,"passed_time":49.54214365,"remaining_time":92.0068382},
{"learn":[112859.3886],"iteration":175,"passed_time":49.84774009,"remaining_time":91.76515789},
{"learn":[112754.1773],"iteration":176,"passed_time":50.15805075,"remaining_time":91.53135814},
{"learn":[112658.9234],"iteration":177,"passed_time":50.45762496,"remaining_time":91.27727661},
{"learn":[112654.874],"iteration":178,"passed_time":50.47481678,"remaining_time":90.51629154},
{"learn":[112554.7609],"iteration":179,"passed_time":50.77464842,"remaining_time":90.26604164},
{"learn":[112475.3891],"iteration":180,"passed_time":51.0828883,"remaining_time":90.0300628},
{"learn":[112472.9549],"iteration":181,"passed_time":51.09614355,"remaining_time":89.27787719},
{"learn":[112461.1785],"iteration":182,"passed_time":51.40332539,"remaining_time":89.04291884},
{"learn":[112432.2928],"iteration":183,"passed_time":51.70850267,"remaining_time":88.80373284},
{"learn":[112413.641],"iteration":184,"passed_time":52.0125594,"remaining_time":88.56192547},
{"learn":[112248.1025],"iteration":185,"passed_time":52.33174919,"remaining_time":88.34499595},
{"learn":[112196.5977],"iteration":186,"passed_time":52.63954876,"remaining_time":88.10790782},
{"learn":[112130.7808],"iteration":187,"passed_time":52.9417793,"remaining_time":87.86082522},
{"learn":[112128.2904],"iteration":188,"passed_time":52.95909667,"remaining_time":87.14433367},
{"learn":[112065.4718],"iteration":189,"passed_time":53.27144453,"remaining_time":86.91656739},
{"learn":[112026.9686],"iteration":190,"passed_time":53.57760673,"remaining_time":86.67790827},
{"learn":[111944.321],"iteration":191,"passed_time":53.88769871,"remaining_time":86.44485001},
{"learn":[111922.7193],"iteration":192,"passed_time":54.19151392,"remaining_time":86.20100919},
{"learn":[111818.5536],"iteration":193,"passed_time":54.50295706,"remaining_time":85.96858176},
{"learn":[111718.8014],"iteration":194,"passed_time":54.80475627,"remaining_time":85.72025981},
{"learn":[111650.3009],"iteration":195,"passed_time":55.10902732,"remaining_time":85.47522605},
{"learn":[111633.4057],"iteration":196,"passed_time":55.42671324,"remaining_time":85.25022391},
{"learn":[111628.2757],"iteration":197,"passed_time":55.4511582,"remaining_time":84.57701908},
{"learn":[111610.9716],"iteration":198,"passed_time":55.75575877,"remaining_time":84.33408738},
{"learn":[111598.419],"iteration":199,"passed_time":55.77095567,"remaining_time":83.6564335},
{"learn":[111394.745],"iteration":200,"passed_time":56.07521148,"remaining_time":83.41536433},
{"learn":[111390.4002],"iteration":201,"passed_time":56.08961138,"remaining_time":82.74606035},
{"learn":[111374.5862],"iteration":202,"passed_time":56.39663574,"remaining_time":82.51133406},
{"learn":[111369.2322],"iteration":203,"passed_time":56.44515854,"remaining_time":81.90081827},
{"learn":[111327.6803],"iteration":204,"passed_time":56.75294458,"remaining_time":81.66887146},
{"learn":[111290.351],"iteration":205,"passed_time":57.0595305,"remaining_time":81.43447557},
{"learn":[111246.6375],"iteration":206,"passed_time":57.36976435,"remaining_time":81.20454567},
{"learn":[111231.615],"iteration":207,"passed_time":57.67478814,"remaining_time":80.9665295},
{"learn":[111229.5168],"iteration":208,"passed_time":57.69841896,"remaining_time":80.33607617},
{"learn":[111161.9409],"iteration":209,"passed_time":57.99774541,"remaining_time":80.09212461},
{"learn":[111155.0687],"iteration":210,"passed_time":58.04625761,"remaining_time":79.50411587},
{"learn":[111143.0896],"iteration":211,"passed_time":58.36246653,"remaining_time":79.28486019},
{"learn":[110952.7394],"iteration":212,"passed_time":58.41136939,"remaining_time":78.7045212},
{"learn":[110883.2724],"iteration":213,"passed_time":58.71335092,"remaining_time":78.46737553},
{"learn":[110664.2193],"iteration":214,"passed_time":59.01654741,"remaining_time":78.23123727},
{"learn":[110622.6604],"iteration":215,"passed_time":59.32862024,"remaining_time":78.00614884},
{"learn":[110602.1933],"iteration":216,"passed_time":59.6333368,"remaining_time":77.77066505},
{"learn":[110545.0639],"iteration":217,"passed_time":59.94228949,"remaining_time":77.54002586},
{"learn":[110505.6603],"iteration":218,"passed_time":60.25399251,"remaining_time":77.31220044},
{"learn":[110363.4879],"iteration":219,"passed_time":60.56156164,"remaining_time":77.07835118},
{"learn":[110334.0174],"iteration":220,"passed_time":60.86419015,"remaining_time":76.83759753},
{"learn":[110325.1722],"iteration":221,"passed_time":60.89717831,"remaining_time":76.25862869},
{"learn":[110317.4913],"iteration":222,"passed_time":60.9128075,"remaining_time":75.66299407},
{"learn":[110301.7451],"iteration":223,"passed_time":61.21518753,"remaining_time":75.42585607},
{"learn":[110273.6454],"iteration":224,"passed_time":61.52069408,"remaining_time":75.19195943},
{"learn":[110236.5937],"iteration":225,"passed_time":61.82841819,"remaining_time":74.96011763},
{"learn":[110223.0676],"iteration":226,"passed_time":62.13754237,"remaining_time":74.72929105},
{"learn":[110209.2254],"iteration":227,"passed_time":62.44936276,"remaining_time":74.50099418},
{"learn":[110192.9295],"iteration":228,"passed_time":62.75351279,"remaining_time":74.26289068},
{"learn":[110093.7244],"iteration":229,"passed_time":63.07587321,"remaining_time":74.04559029},
{"learn":[110079.3267],"iteration":230,"passed_time":63.39843678,"remaining_time":73.82761686},
{"learn":[110033.93],"iteration":231,"passed_time":63.70306855,"remaining_time":73.58802747},
{"learn":[110008.9198],"iteration":232,"passed_time":64.0107848,"remaining_time":73.35141434},
{"learn":[109970.2215],"iteration":233,"passed_time":64.31735522,"remaining_time":73.11289098},
{"learn":[109949.9799],"iteration":234,"passed_time":64.61525319,"remaining_time":72.86400892},
{"learn":[109910.8567],"iteration":235,"passed_time":64.9218253,"remaining_time":72.62441474},
{"learn":[109823.9488],"iteration":236,"passed_time":65.23529609,"remaining_time":72.39191085},
{"learn":[109821.1007],"iteration":237,"passed_time":65.28562752,"remaining_time":71.86905214},
{"learn":[109800.6487],"iteration":238,"passed_time":65.59661919,"remaining_time":71.63480171},
{"learn":[109785.896],"iteration":239,"passed_time":65.90570433,"remaining_time":71.39784636},
{"learn":[109708.31],"iteration":240,"passed_time":66.21077741,"remaining_time":71.1559807},
{"learn":[109652.7177],"iteration":241,"passed_time":66.52019513,"remaining_time":70.91822456},
{"learn":[109632.0726],"iteration":242,"passed_time":66.82704983,"remaining_time":70.67716793},
{"learn":[109551.8737],"iteration":243,"passed_time":67.12906307,"remaining_time":70.4304924},
{"learn":[109518.1819],"iteration":244,"passed_time":67.18015847,"remaining_time":69.92220576},
{"learn":[109515.8169],"iteration":245,"passed_time":67.2031939,"remaining_time":69.38866362},
{"learn":[109501.8458],"iteration":246,"passed_time":67.51560209,"remaining_time":69.1556572},
{"learn":[109489.6293],"iteration":247,"passed_time":67.81862094,"remaining_time":68.91246967},
{"learn":[109465.5806],"iteration":248,"passed_time":68.12730813,"remaining_time":68.67451543},
{"learn":[109420.3014],"iteration":249,"passed_time":68.44015002,"remaining_time":68.44015002},
{"learn":[109374.8118],"iteration":250,"passed_time":68.7475201,"remaining_time":68.1997311},
{"learn":[109268.9924],"iteration":251,"passed_time":69.0548449,"remaining_time":67.95873625},
{"learn":[109255.6102],"iteration":252,"passed_time":69.35892997,"remaining_time":67.71405416},
{"learn":[109221.643],"iteration":253,"passed_time":69.66777481,"remaining_time":67.47351418},
{"learn":[109109.014],"iteration":254,"passed_time":69.97519791,"remaining_time":67.2310725},
{"learn":[109081.4996],"iteration":255,"passed_time":70.28119407,"remaining_time":66.98676309},
{"learn":[109065.0269],"iteration":256,"passed_time":70.29704215,"remaining_time":66.46763129},
{"learn":[109049.5919],"iteration":257,"passed_time":70.60444277,"remaining_time":66.22587267},
{"learn":[108951.396],"iteration":258,"passed_time":70.91686944,"remaining_time":65.98828391},
{"learn":[108934.9897],"iteration":259,"passed_time":71.22853455,"remaining_time":65.74941651},
{"learn":[108782.991],"iteration":260,"passed_time":71.5338368,"remaining_time":65.50416473},
{"learn":[108773.0346],"iteration":261,"passed_time":71.83972688,"remaining_time":65.25898854},
{"learn":[108707.6829],"iteration":262,"passed_time":72.15354388,"remaining_time":65.02049391},
{"learn":[108690.0695],"iteration":263,"passed_time":72.4590205,"remaining_time":64.77397287},
{"learn":[108585.7533],"iteration":264,"passed_time":72.4758704,"remaining_time":64.27105488},
{"learn":[108534.2185],"iteration":265,"passed_time":72.78409779,"remaining_time":64.02811611},
{"learn":[108477.4437],"iteration":266,"passed_time":73.0891116,"remaining_time":63.7818839},
{"learn":[108448.7564],"iteration":267,"passed_time":73.12094068,"remaining_time":63.29872477},
{"learn":[108447.1896],"iteration":268,"passed_time":73.13611895,"remaining_time":62.80462259},
{"learn":[108407.4546],"iteration":269,"passed_time":73.44011364,"remaining_time":62.56009681},
{"learn":[108406.3362],"iteration":270,"passed_time":73.45737509,"remaining_time":62.07283725},
{"learn":[108343.7079],"iteration":271,"passed_time":73.76872688,"remaining_time":61.83555048},
{"learn":[108185.5595],"iteration":272,"passed_time":74.07179056,"remaining_time":61.59082951},
{"learn":[108135.7129],"iteration":273,"passed_time":74.38194302,"remaining_time":61.35152964},
{"learn":[108134.7175],"iteration":274,"passed_time":74.39863988,"remaining_time":60.87161445},
{"learn":[108109.7901],"iteration":275,"passed_time":74.70940938,"remaining_time":60.63372356},
{"learn":[108080.8149],"iteration":276,"passed_time":75.02104326,"remaining_time":60.39600233},
{"learn":[108045.7086],"iteration":277,"passed_time":75.33279733,"remaining_time":60.15784535},
{"learn":[108020.0632],"iteration":278,"passed_time":75.63625561,"remaining_time":59.91258957},
{"learn":[107972.8962],"iteration":279,"passed_time":75.94022517,"remaining_time":59.66731978},
{"learn":[107971.9588],"iteration":280,"passed_time":75.9557186,"remaining_time":59.1968056},
{"learn":[107963.4115],"iteration":281,"passed_time":76.25987061,"remaining_time":58.95266593},
{"learn":[107923.5194],"iteration":282,"passed_time":76.57362349,"remaining_time":58.71546395},
{"learn":[107896.9661],"iteration":283,"passed_time":76.88432484,"remaining_time":58.47540199},
{"learn":[107864.9293],"iteration":284,"passed_time":77.1909021,"remaining_time":58.23173316},
{"learn":[107666.9922],"iteration":285,"passed_time":77.50187242,"remaining_time":57.99091153},
{"learn":[107665.6167],"iteration":286,"passed_time":77.51967831,"remaining_time":57.53202606},
{"learn":[107635.5879],"iteration":287,"passed_time":77.82665174,"remaining_time":57.28906309},
{"learn":[107624.3526],"iteration":288,"passed_time":78.13486906,"remaining_time":57.0465653},
{"learn":[107537.338],"iteration":289,"passed_time":78.43686844,"remaining_time":56.79911163},
{"learn":[107518.3657],"iteration":290,"passed_time":78.75083233,"remaining_time":56.55987614},
{"learn":[107409.707],"iteration":291,"passed_time":79.05519372,"remaining_time":56.31328868},
{"learn":[107404.2547],"iteration":292,"passed_time":79.36283096,"remaining_time":56.06862119},
{"learn":[107317.5777],"iteration":293,"passed_time":79.66978189,"remaining_time":55.82304446},
{"learn":[107299.1567],"iteration":294,"passed_time":79.97377338,"remaining_time":55.57499506},
{"learn":[107267.4739],"iteration":295,"passed_time":80.28338858,"remaining_time":55.33044348},
{"learn":[107239],"iteration":296,"passed_time":80.58037987,"remaining_time":55.0768253},
{"learn":[107160.9409],"iteration":297,"passed_time":80.88529904,"remaining_time":54.82828995},
{"learn":[107111.25],"iteration":298,"passed_time":81.19198764,"remaining_time":54.58056694},
{"learn":[107065.6829],"iteration":299,"passed_time":81.48836313,"remaining_time":54.32557542},
{"learn":[107043.3029],"iteration":300,"passed_time":81.79297495,"remaining_time":54.0757542},
{"learn":[107020.7208],"iteration":301,"passed_time":82.09760863,"remaining_time":53.82558447},
{"learn":[107020.0124],"iteration":302,"passed_time":82.11275326,"remaining_time":53.38683958},
{"learn":[106914.432],"iteration":303,"passed_time":82.41770631,"remaining_time":53.1377317},
{"learn":[106883.6728],"iteration":304,"passed_time":82.72215029,"remaining_time":52.88793215},
{"learn":[106877.2986],"iteration":305,"passed_time":83.02995738,"remaining_time":52.63990762},
{"learn":[106875.5308],"iteration":306,"passed_time":83.05273374,"remaining_time":52.21230492},
{"learn":[106857.3725],"iteration":307,"passed_time":83.36543558,"remaining_time":51.96806374},
{"learn":[106800.5179],"iteration":308,"passed_time":83.68373352,"remaining_time":51.72683852},
{"learn":[106790.0568],"iteration":309,"passed_time":83.99074628,"remaining_time":51.47819933},
{"learn":[106787.3057],"iteration":310,"passed_time":84.29295997,"remaining_time":51.22626828},
{"learn":[106757.9814],"iteration":311,"passed_time":84.59410924,"remaining_time":50.97337351},
{"learn":[106731.6009],"iteration":312,"passed_time":84.89663446,"remaining_time":50.72099247},
{"learn":[106712.2373],"iteration":313,"passed_time":85.20289878,"remaining_time":50.47050692},
{"learn":[106495.8749],"iteration":314,"passed_time":85.51115787,"remaining_time":50.22083875},
{"learn":[106416.0581],"iteration":315,"passed_time":85.81508568,"remaining_time":49.96827774},
{"learn":[106364.1589],"iteration":316,"passed_time":86.13025794,"remaining_time":49.72188392},
{"learn":[106358.7302],"iteration":317,"passed_time":86.43343844,"remaining_time":49.46819433},
{"learn":[106337.4334],"iteration":318,"passed_time":86.74043313,"remaining_time":49.21635861},
{"learn":[106311.5979],"iteration":319,"passed_time":87.05025604,"remaining_time":48.96576902},
{"learn":[106213.3486],"iteration":320,"passed_time":87.35398307,"remaining_time":48.71141112},
{"learn":[106205.2543],"iteration":321,"passed_time":87.66637024,"remaining_time":48.46153386},
{"learn":[106183.0379],"iteration":322,"passed_time":87.98235714,"remaining_time":48.21324215},
{"learn":[106121.6038],"iteration":323,"passed_time":88.29586268,"remaining_time":47.96318467},
{"learn":[106107.4878],"iteration":324,"passed_time":88.59944361,"remaining_time":47.70739271},
{"learn":[106056.8045],"iteration":325,"passed_time":88.91015938,"remaining_time":47.45511574},
{"learn":[106052.5717],"iteration":326,"passed_time":88.94417578,"remaining_time":47.056093},
{"learn":[106043.7322],"iteration":327,"passed_time":89.0987334,"remaining_time":46.72250654},
{"learn":[105978.0417],"iteration":328,"passed_time":89.40849976,"remaining_time":46.47067921},
{"learn":[105958.4834],"iteration":329,"passed_time":89.71033776,"remaining_time":46.21441642},
{"learn":[105943.1764],"iteration":330,"passed_time":90.01340728,"remaining_time":45.95850704},
{"learn":[105932.4136],"iteration":331,"passed_time":90.32403936,"remaining_time":45.7061404},
{"learn":[105931.5583],"iteration":332,"passed_time":90.34288171,"remaining_time":45.30709083},
{"learn":[105918.5844],"iteration":333,"passed_time":90.65706104,"remaining_time":45.0571022},
{"learn":[105918.0967],"iteration":334,"passed_time":90.67132563,"remaining_time":44.65901113},
{"learn":[105872.2662],"iteration":335,"passed_time":90.97831669,"remaining_time":44.40608315},
{"learn":[105822.157],"iteration":336,"passed_time":91.29513033,"remaining_time":44.15758529},
{"learn":[105789.9334],"iteration":337,"passed_time":91.60357805,"remaining_time":43.9046735},
{"learn":[105736.0024],"iteration":338,"passed_time":91.90845715,"remaining_time":43.64973923},
{"learn":[105722.043],"iteration":339,"passed_time":92.21801383,"remaining_time":43.39671239},
{"learn":[105649.8168],"iteration":340,"passed_time":92.52169021,"remaining_time":43.14061215},
{"learn":[105634.659],"iteration":341,"passed_time":92.83471856,"remaining_time":42.88855419},
{"learn":[105630.8026],"iteration":342,"passed_time":93.13472481,"remaining_time":42.63018016},
{"learn":[105528.9752],"iteration":343,"passed_time":93.43934783,"remaining_time":42.37365774},
{"learn":[105513.8661],"iteration":344,"passed_time":93.73978085,"remaining_time":42.114974},
{"learn":[105473.9309],"iteration":345,"passed_time":94.04455254,"remaining_time":41.85798003},
{"learn":[105460.1593],"iteration":346,"passed_time":94.35484861,"remaining_time":41.6031465},
{"learn":[105447.4508],"iteration":347,"passed_time":94.66454966,"remaining_time":41.34773433},
{"learn":[105412.903],"iteration":348,"passed_time":94.97359661,"remaining_time":41.09172805},
{"learn":[105263.767],"iteration":349,"passed_time":95.2795885,"remaining_time":40.83410936},
{"learn":[105006.786],"iteration":350,"passed_time":95.58145416,"remaining_time":40.57446345},
{"learn":[104976.6398],"iteration":351,"passed_time":95.88453393,"remaining_time":40.31508813},
{"learn":[104974.0286],"iteration":352,"passed_time":95.90728814,"remaining_time":39.93872906},
{"learn":[104967.5544],"iteration":353,"passed_time":96.2146099,"remaining_time":39.68173177},
{"learn":[104958.4844],"iteration":354,"passed_time":96.51819843,"remaining_time":39.42292612},
{"learn":[104958.0519],"iteration":355,"passed_time":96.53548128,"remaining_time":39.04805984},
{"learn":[104942.4792],"iteration":356,"passed_time":96.84079152,"remaining_time":38.79056915},
{"learn":[104905.0627],"iteration":357,"passed_time":97.15222857,"remaining_time":38.5352415},
{"learn":[104892.2257],"iteration":358,"passed_time":97.46155313,"remaining_time":38.27877156},
{"learn":[104869.309],"iteration":359,"passed_time":97.76847386,"remaining_time":38.02107317},
{"learn":[104778.2195],"iteration":360,"passed_time":98.0804714,"remaining_time":37.76505686},
{"learn":[104777.6818],"iteration":361,"passed_time":98.09541688,"remaining_time":37.39549041},
{"learn":[104769.0669],"iteration":362,"passed_time":98.40259993,"remaining_time":37.13817132},
{"learn":[104630.5764],"iteration":363,"passed_time":98.70961312,"remaining_time":36.88051479},
{"learn":[104616.485],"iteration":364,"passed_time":99.02459325,"remaining_time":36.62553449},
{"learn":[104578.0949],"iteration":365,"passed_time":99.33763127,"remaining_time":36.36951527},
{"learn":[104432.5229],"iteration":366,"passed_time":99.6448195,"remaining_time":36.11106538},
{"learn":[104377.1471],"iteration":367,"passed_time":99.94875728,"remaining_time":35.85118468},
{"learn":[104365.2966],"iteration":368,"passed_time":100.2500793,"remaining_time":35.59013656},
{"learn":[104348.2196],"iteration":369,"passed_time":100.5582553,"remaining_time":35.3312789},
{"learn":[104197.3257],"iteration":370,"passed_time":100.8667551,"remaining_time":35.07226795},
{"learn":[104173.7197],"iteration":371,"passed_time":101.1773082,"remaining_time":34.81369744},
{"learn":[104173.1203],"iteration":372,"passed_time":101.2001226,"remaining_time":34.4568782},
{"learn":[104077.1097],"iteration":373,"passed_time":101.3495566,"remaining_time":34.14450304},
{"learn":[104045.5574],"iteration":374,"passed_time":101.6560612,"remaining_time":33.88535373},
{"learn":[103969.7774],"iteration":375,"passed_time":101.9654624,"remaining_time":33.6269078},
{"learn":[103849.6239],"iteration":376,"passed_time":102.2726035,"remaining_time":33.36745418},
{"learn":[103830.2323],"iteration":377,"passed_time":102.5862994,"remaining_time":33.10986382},
{"learn":[103798.9329],"iteration":378,"passed_time":102.8956678,"remaining_time":32.85059579},
{"learn":[103725.6089],"iteration":379,"passed_time":103.2038013,"remaining_time":32.59067409},
{"learn":[103705.474],"iteration":380,"passed_time":103.5099527,"remaining_time":32.32988025},
{"learn":[103693.8861],"iteration":381,"passed_time":103.8136058,"remaining_time":32.0680772},
{"learn":[103660.9942],"iteration":382,"passed_time":104.1279412,"remaining_time":31.80931885},
{"learn":[103657.6666],"iteration":383,"passed_time":104.145301,"remaining_time":31.46055968},
{"learn":[103611.9913],"iteration":384,"passed_time":104.458198,"remaining_time":31.2017994},
{"learn":[103463.6144],"iteration":385,"passed_time":104.7632316,"remaining_time":30.94043627},
{"learn":[103397.8786],"iteration":386,"passed_time":105.071065,"remaining_time":30.67966496},
{"learn":[103312.4078],"iteration":387,"passed_time":105.3741275,"remaining_time":30.41727393},
{"learn":[103303.5482],"iteration":388,"passed_time":105.6835406,"remaining_time":30.15648587},
{"learn":[103140.064],"iteration":389,"passed_time":105.9932159,"remaining_time":29.89552242},
{"learn":[103129.0263],"iteration":390,"passed_time":106.3018271,"remaining_time":29.63401317},
{"learn":[103107.1181],"iteration":391,"passed_time":106.6092804,"remaining_time":29.37194459},
{"learn":[103058.97],"iteration":392,"passed_time":106.9152131,"remaining_time":29.10923105},
{"learn":[103019.6587],"iteration":393,"passed_time":107.2185538,"remaining_time":28.84560076},
{"learn":[103004.5163],"iteration":394,"passed_time":107.5225121,"remaining_time":28.5819336},
{"learn":[102983.3486],"iteration":395,"passed_time":107.8373864,"remaining_time":28.32092975},
{"learn":[102983.0817],"iteration":396,"passed_time":107.8533039,"remaining_time":27.98209145},
{"learn":[102937.8965],"iteration":397,"passed_time":108.1586821,"remaining_time":27.71905922},
{"learn":[102860.7871],"iteration":398,"passed_time":108.4606972,"remaining_time":27.45496346},
{"learn":[102841.4313],"iteration":399,"passed_time":108.7660459,"remaining_time":27.19151148},
{"learn":[102841.1874],"iteration":400,"passed_time":108.7779338,"remaining_time":26.85540013},
{"learn":[102828.7302],"iteration":401,"passed_time":109.0838868,"remaining_time":26.59258933},
{"learn":[102827.2754],"iteration":402,"passed_time":109.1001376,"remaining_time":26.25983462},
{"learn":[102815.6816],"iteration":403,"passed_time":109.4139922,"remaining_time":25.99936447},
{"learn":[102781.1347],"iteration":404,"passed_time":109.7222608,"remaining_time":25.73732044},
{"learn":[102755.8488],"iteration":405,"passed_time":110.0346467,"remaining_time":25.47600194},
{"learn":[102748.1971],"iteration":406,"passed_time":110.3387637,"remaining_time":25.21254306},
{"learn":[102673.3307],"iteration":407,"passed_time":110.6418264,"remaining_time":24.94864713},
{"learn":[102658.1265],"iteration":408,"passed_time":110.976597,"remaining_time":24.69161449},
{"learn":[102644.6695],"iteration":409,"passed_time":111.2839611,"remaining_time":24.42818659},
{"learn":[102540.4671],"iteration":410,"passed_time":111.5927446,"remaining_time":24.16485223},
{"learn":[102534.295],"iteration":411,"passed_time":111.8984907,"remaining_time":23.9006485},
{"learn":[102528.0183],"iteration":412,"passed_time":111.9479498,"remaining_time":23.58225578},
{"learn":[102508.3846],"iteration":413,"passed_time":112.1007359,"remaining_time":23.2866263},
{"learn":[102386.692],"iteration":414,"passed_time":112.4060084,"remaining_time":23.02291739},
{"learn":[102360.5357],"iteration":415,"passed_time":112.7073298,"remaining_time":22.75821082},
{"learn":[102347.3903],"iteration":416,"passed_time":113.0179223,"remaining_time":22.49517397},
{"learn":[102335.748],"iteration":417,"passed_time":113.3256688,"remaining_time":22.2313513},
{"learn":[102334.7711],"iteration":418,"passed_time":113.3440341,"remaining_time":21.91137652},
{"learn":[102316.2967],"iteration":419,"passed_time":113.6542389,"remaining_time":21.64842646},
{"learn":[102226.5773],"iteration":420,"passed_time":113.9528739,"remaining_time":21.38308085},
{"learn":[102098.3114],"iteration":421,"passed_time":114.25568,"remaining_time":21.11834843},
{"learn":[102093.2876],"iteration":422,"passed_time":114.3092,"remaining_time":20.80805767},
{"learn":[102087.7051],"iteration":423,"passed_time":114.6248179,"remaining_time":20.54595793},
{"learn":[102077.2793],"iteration":424,"passed_time":114.936426,"remaining_time":20.2828987},
{"learn":[101957.7945],"iteration":425,"passed_time":115.2466665,"remaining_time":20.019374},
{"learn":[101921.6641],"iteration":426,"passed_time":115.5549717,"remaining_time":19.7552996},
{"learn":[101904.9482],"iteration":427,"passed_time":115.8579914,"remaining_time":19.4901294},
{"learn":[101904.7199],"iteration":428,"passed_time":115.8729833,"remaining_time":19.17711379},
{"learn":[101898.4394],"iteration":429,"passed_time":116.1799902,"remaining_time":18.91302166},
{"learn":[101857.4326],"iteration":430,"passed_time":116.4893883,"remaining_time":18.64911321},
{"learn":[101837.9924],"iteration":431,"passed_time":116.8035514,"remaining_time":18.3857442},
{"learn":[101791.6797],"iteration":432,"passed_time":117.1138117,"remaining_time":18.12153668},
{"learn":[101761.9612],"iteration":433,"passed_time":117.4156712,"remaining_time":17.8558394},
{"learn":[101757.4774],"iteration":434,"passed_time":117.7245164,"remaining_time":17.59101969},
{"learn":[101757.0397],"iteration":435,"passed_time":117.7479317,"remaining_time":17.28410006},
{"learn":[101749.1074],"iteration":436,"passed_time":118.0481165,"remaining_time":17.01837836},
{"learn":[101695.0703],"iteration":437,"passed_time":118.3548605,"remaining_time":16.75342774},
{"learn":[101527.8996],"iteration":438,"passed_time":118.6674797,"remaining_time":16.4891031},
{"learn":[101503.6772],"iteration":439,"passed_time":118.978648,"remaining_time":16.22436109},
{"learn":[101397.8119],"iteration":440,"passed_time":119.2826694,"remaining_time":15.95845237},
{"learn":[101375.9219],"iteration":441,"passed_time":119.5950498,"remaining_time":15.69346808},
{"learn":[101354.3371],"iteration":442,"passed_time":119.9024238,"remaining_time":15.42762563},
{"learn":[101340.6448],"iteration":443,"passed_time":120.2152395,"remaining_time":15.16228246},
{"learn":[101302.7941],"iteration":444,"passed_time":120.5228426,"remaining_time":14.89608167},
{"learn":[101299.8649],"iteration":445,"passed_time":120.8321946,"remaining_time":14.62990697},
{"learn":[101286.0489],"iteration":446,"passed_time":121.1488236,"remaining_time":14.36440191},
{"learn":[101273.8153],"iteration":447,"passed_time":121.456423,"remaining_time":14.09762052},
{"learn":[101250.6435],"iteration":448,"passed_time":121.7644591,"remaining_time":13.83070694},
{"learn":[101198.1264],"iteration":449,"passed_time":122.0777904,"remaining_time":13.56419893},
{"learn":[101174.6763],"iteration":450,"passed_time":122.3885738,"remaining_time":13.29720647},
{"learn":[101167.0429],"iteration":451,"passed_time":122.7018504,"remaining_time":13.03028499},
{"learn":[101065.1996],"iteration":452,"passed_time":123.0143762,"remaining_time":12.76308098},
{"learn":[101017.8664],"iteration":453,"passed_time":123.3262997,"remaining_time":12.49561627},
{"learn":[100956.8789],"iteration":454,"passed_time":123.3587077,"remaining_time":12.20031175},
{"learn":[100952.023],"iteration":455,"passed_time":123.6642027,"remaining_time":11.93251079},
{"learn":[100942.6069],"iteration":456,"passed_time":123.9713933,"remaining_time":11.6647044},
{"learn":[100844.8322],"iteration":457,"passed_time":124.2795565,"remaining_time":11.39681522},
{"learn":[100835.0574],"iteration":458,"passed_time":124.5900228,"remaining_time":11.12895628},
{"learn":[100824.5853],"iteration":459,"passed_time":124.8949669,"remaining_time":10.8604319},
{"learn":[100787.1978],"iteration":460,"passed_time":125.2028882,"remaining_time":10.59200139},
{"learn":[100763.1923],"iteration":461,"passed_time":125.5157491,"remaining_time":10.3238062},
{"learn":[100750.5494],"iteration":462,"passed_time":125.8269934,"remaining_time":10.05528889},
{"learn":[100576.6583],"iteration":463,"passed_time":126.1349247,"remaining_time":9.786330367},
{"learn":[100552.4983],"iteration":464,"passed_time":126.4470912,"remaining_time":9.517522991},
{"learn":[100544.522],"iteration":465,"passed_time":126.7481134,"remaining_time":9.247716425},
{"learn":[100388.048],"iteration":466,"passed_time":127.0596258,"remaining_time":8.978517454},
{"learn":[100382.5536],"iteration":467,"passed_time":127.3592202,"remaining_time":8.708322748},
{"learn":[100374.929],"iteration":468,"passed_time":127.6615874,"remaining_time":8.438185946},
{"learn":[100365.0504],"iteration":469,"passed_time":127.8123393,"remaining_time":8.158234422},
{"learn":[100303.9129],"iteration":470,"passed_time":128.119745,"remaining_time":7.888476869},
{"learn":[100300.641],"iteration":471,"passed_time":128.4256988,"remaining_time":7.618473659},
{"learn":[100264.238],"iteration":472,"passed_time":128.7263593,"remaining_time":7.348016284},
{"learn":[100248.8333],"iteration":473,"passed_time":129.0358147,"remaining_time":7.077913885},
{"learn":[100213.3102],"iteration":474,"passed_time":129.3477164,"remaining_time":6.807774545},
{"learn":[100161.32],"iteration":475,"passed_time":129.6591365,"remaining_time":6.537435453},
{"learn":[100150.7543],"iteration":476,"passed_time":129.9713689,"remaining_time":6.266963279},
{"learn":[100147.5347],"iteration":477,"passed_time":130.2692741,"remaining_time":5.995656969},
{"learn":[100145.7924],"iteration":478,"passed_time":130.5720679,"remaining_time":5.724453915},
{"learn":[100069.5689],"iteration":479,"passed_time":130.8831914,"remaining_time":5.453466308},
{"learn":[100069.0854],"iteration":480,"passed_time":130.8991506,"remaining_time":5.17065252},
{"learn":[100068.9488],"iteration":481,"passed_time":130.9151981,"remaining_time":4.888949306},
{"learn":[100038.2175],"iteration":482,"passed_time":131.2243084,"remaining_time":4.618660959},
{"learn":[100027.1841],"iteration":483,"passed_time":131.5331063,"remaining_time":4.348201861},
{"learn":[100026.9783],"iteration":484,"passed_time":131.5499262,"remaining_time":4.06855442},
{"learn":[99969.38496],"iteration":485,"passed_time":131.8604127,"remaining_time":3.798448104},
{"learn":[99951.88763],"iteration":486,"passed_time":132.1727846,"remaining_time":3.528226284},
{"learn":[99919.91433],"iteration":487,"passed_time":132.4755204,"remaining_time":3.257594763},
{"learn":[99765.41434],"iteration":488,"passed_time":132.7767239,"remaining_time":2.986797471},
{"learn":[99735.5467],"iteration":489,"passed_time":133.0872435,"remaining_time":2.716066195},
{"learn":[99717.20988],"iteration":490,"passed_time":133.3935298,"remaining_time":2.44509525},
{"learn":[99698.19925],"iteration":491,"passed_time":133.7084652,"remaining_time":2.174121385},
{"learn":[99673.70046],"iteration":492,"passed_time":134.0219721,"remaining_time":1.902948894},
{"learn":[99642.92774],"iteration":493,"passed_time":134.3262984,"remaining_time":1.631493503},
{"learn":[99635.15198],"iteration":494,"passed_time":134.3418895,"remaining_time":1.356988783},
{"learn":[99612.3588],"iteration":495,"passed_time":134.6507202,"remaining_time":1.085892905},
{"learn":[99612.18615],"iteration":496,"passed_time":134.6703106,"remaining_time":0.8128992593},
{"learn":[99609.86764],"iteration":497,"passed_time":134.9772875,"remaining_time":0.5420774596},
{"learn":[99454.95012],"iteration":498,"passed_time":135.2862303,"remaining_time":0.2711146899},
{"learn":[99336.04845],"iteration":499,"passed_time":135.592349,"remaining_time":0}
]}